{
  "name": "GTFS_stop_times",
  "owner": "it_palermo",
  "name_dataset": "stop_times",
  "src":
    {
      "type": "csv",
      "url": "/Users/lilloraffa/Development/data/opendata/mob/gtfs/it_palermo/stop_times.txt",
      "inj_src": "ftp"
    },
  "std_schema": "schema-gtfs_stop_times",
  "fields_conv":
    [
      {
        "field_std": "trip_id",
        "formula": "trip_id"
      },
      {
        "field_std": "arrival_time",
        "formula": "arrival_time"
      },
      {
        "field_std": "departure_time",
        "formula": "departure_time"
      },
      {
        "field_std": "stop_id",
        "formula": "stop_id"
      },
      {
        "field_std": "stop_sequence",
        "formula": "stop_sequence"
      },
      {
        "field_std": "stop_headsign",
        "formula": "stop_headsign"
      },
      {
        "field_std": "pickup_type",
        "formula": "pickup_type"
      },
      {
        "field_std": "drop_off_type",
        "formula": "drop_off_type"
      },
      {
        "field_std": "shape_dist_traveled",
        "formula": "shape_dist_traveled"
      }
    ]

}
